{
    "defend": [
        "infamy",
        "shevárdino",
        "position",
        "town"
    ],
    "think": [
        "nichola",
        "princess",
        "anatole",
        "matter",
        "count",
        "officer",
        "today",
        "expedition",
        "thing",
        "life",
        "regiment",
        "moment",
        "campaign",
        "Túshin",
        "diplomatist",
        "rascal",
        "countess",
        "battle",
        "tomorrow",
        "ilyá",
        "science",
        "perónskaya",
        "véra",
        "quill",
        "thought",
        "dessalle",
        "war",
        "emperor",
        "night",
        "sale",
        "descent",
        "place",
        "wolzogen",
        "mademoiselle",
        "love",
        "woman",
        "Platón",
        "man",
        "historian"
    ],
    "understand": [
        "significance",
        "word",
        "life",
        "count",
        "question",
        "thing",
        "emperor",
        "self",
        "revolution",
        "anatole",
        "fondness",
        "boldness",
        "sum",
        "fédya",
        "insignificance",
        "nichola",
        "people",
        "mood",
        "matter",
        "situation",
        "deception",
        "balashëv",
        "symptom",
        "princess",
        "cruelty",
        "military",
        "goodness",
        "law",
        "love",
        "delight",
        "value",
        "working",
        "construction",
        "side",
        "importance",
        "news",
        "peasant",
        "joy",
        "child"
    ],
    "believe": [
        "word",
        "expert",
        "nonsense",
        "victory"
    ],
    "capture": [
        "tongue",
        "king",
        "marshal",
        "vessel",
        "fortress",
        "flèche",
        "part",
        "russian",
        "murat",
        "army",
        "prisoner"
    ],
    "want": [
        "sir",
        "nichola",
        "baron",
        "liberty",
        "carriage",
        "count",
        "money",
        "argument",
        "wolf",
        "son",
        "taste",
        "question",
        "sacrifice",
        "pólya",
        "tomorrow",
        "word",
        "war",
        "grain",
        "thing",
        "decision",
        "peasant",
        "victim",
        "floor",
        "bit",
        "reward",
        "knife",
        "chat",
        "rain"
    ],
    "show": [
        "impatience",
        "greatness",
        "interest",
        "sign",
        "sympathy",
        "baron",
        "paper",
        "figure",
        "crease",
        "uneasiness",
        "pleasure",
        "excitement",
        "alarm",
        "blood",
        "distrust",
        "change",
        "time",
        "way",
        "prisoner",
        "necessity",
        "door",
        "embarrassment",
        "possibility",
        "animation",
        "advantage",
        "rent",
        "indecision",
        "scar",
        "bag",
        "tension",
        "human",
        "pity",
        "partiality",
        "consideration",
        "connection",
        "man"
    ],
    "discuss": [
        "murder",
        "politic",
        "arrangement",
        "estate",
        "advantage",
        "position",
        "siege",
        "direction",
        "matter",
        "baby"
    ],
    "make": [
        "sign",
        "use",
        "peace",
        "way",
        "effort",
        "mistake",
        "thing",
        "haste",
        "fun",
        "plan",
        "man",
        "friend",
        "fool",
        "room",
        "acquaintance",
        "sacrifice",
        "princess",
        "scene",
        "remark",
        "other",
        "countess",
        "officer",
        "difficulty",
        "love",
        "list",
        "exception",
        "preparation",
        "nation",
        "glass",
        "sofa",
        "mess",
        "income",
        "place",
        "will",
        "count",
        "scratch",
        "departure",
        "track",
        "bayonet",
        "reflection",
        "proposal",
        "proposition",
        "expedition",
        "tour",
        "career",
        "eye",
        "sleeker",
        "application",
        "appointment",
        "rush",
        "gentleman",
        "thousand",
        "head",
        "motion",
        "town",
        "joke",
        "public",
        "patient",
        "heart",
        "constitution",
        "Cossack",
        "village",
        "end",
        "arrangement",
        "dash",
        "attack",
        "sport",
        "mésalliance",
        "inquiry",
        "butler",
        "generation",
        "air",
        "campfire",
        "petersburg",
        "movement",
        "cossack",
        "excursion",
        "choice",
        "impression",
        "suggestion",
        "semicircle",
        "story",
        "flame",
        "soldier",
        "mankind",
        "colonel",
        "hobby",
        "concession",
        "life",
        "demand",
        "frenchman",
        "action",
        "fall"
    ],
    "smile": [
        "lip",
        "madame",
        "mademoiselle",
        "aah",
        "véra",
        "freemasonry",
        "Pelagéya",
        "alexander",
        "birch",
        "absent",
        "nichola",
        "eye",
        "balashëv",
        "les",
        "jealo"
    ],
    "produce": [
        "event",
        "effect",
        "queer",
        "davout",
        "argument",
        "chief",
        "revolution",
        "conquest",
        "movement",
        "heat",
        "electricity",
        "migration"
    ],
    "move": [
        "chair",
        "troop",
        "infantry",
        "mountain",
        "people",
        "nation",
        "table",
        "murat",
        "horse",
        "hair",
        "soldier",
        "masse",
        "line",
        "muscle",
        "foot",
        "leg",
        "shadow",
        "eastward",
        "princess",
        "voice",
        "gun",
        "coach",
        "ship",
        "vessel",
        "trunk",
        "hand",
        "baggage",
        "column",
        "humanity"
    ],
    "visit": [
        "friend",
        "mademoiselle",
        "count",
        "Ryazán",
        "karágin",
        "kitchen",
        "nichola",
        "theater",
        "foundling",
        "night"
    ],
    "inquire": [
        "glance",
        "whisper",
        "Túshin",
        "nurse",
        "sympathizer",
        "eye",
        "expression"
    ],
    "save": [
        "army",
        "child",
        "world",
        "mankind",
        "life",
        "power"
    ],
    "ask": [
        "princess",
        "countess",
        "nichola",
        "question",
        "count",
        "permission",
        "emperor",
        "anna",
        "doctor",
        "nesvítski",
        "balashëv",
        "forgiveness",
        "aide",
        "regimental",
        "soldier",
        "officer",
        "artilleryman",
        "anatole",
        "véra",
        "assistant",
        "gerásim",
        "son",
        "opportunity",
        "infantry",
        "colonel",
        "frenchman",
        "accountant",
        "Túshin",
        "driver",
        "newcomer",
        "king",
        "mercy",
        "name",
        "person",
        "arakchéev",
        "destiny",
        "papa",
        "mademoiselle",
        "Balagá",
        "coachman",
        "dessalle",
        "ferapóntov",
        "karp",
        "grapeshot",
        "servant",
        "superintendent",
        "captain",
        "forgive",
        "interpreter",
        "davout",
        "voice",
        "man",
        "Cossack",
        "savélich",
        "boy"
    ],
    "look": [
        "glass",
        "nichola",
        "askance",
        "anna",
        "significance",
        "captain",
        "man",
        "eye",
        "tender",
        "princess",
        "visitor",
        "absent",
        "distraught",
        "day",
        "moment",
        "presentable",
        "Platón",
        "life"
    ],
    "send": [
        "letter",
        "ball",
        "soldier",
        "greeting",
        "official",
        "courier",
        "word",
        "order",
        "ambassador",
        "squadron",
        "countess",
        "news",
        "home",
        "man",
        "huntsman",
        "people",
        "manservant",
        "paper",
        "instruction",
        "number",
        "valet",
        "infantry",
        "reinforcement",
        "police",
        "emperor",
        "army",
        "dispatch",
        "envoy",
        "representative"
    ],
    "present": [
        "arm",
        "state",
        "war",
        "moment",
        "circumstance",
        "time",
        "regiment",
        "one",
        "emperor",
        "joy",
        "bivouac",
        "legion",
        "pearl",
        "uncertainty",
        "quicker",
        "condition",
        "nichola",
        "situation",
        "affair",
        "privation",
        "force",
        "project",
        "example",
        "consciousness",
        "self",
        "princess",
        "accuser",
        "life",
        "activity",
        "complex",
        "move",
        "case"
    ],
    "suggest": [
        "anna",
        "nichola",
        "liveliness",
        "consolation",
        "marriage",
        "lunch",
        "reason"
    ],
    "love": [
        "man",
        "nichola",
        "love",
        "people",
        "anatole",
        "letter",
        "life",
        "story",
        "liberty",
        "woman",
        "darling",
        "devotion",
        "tremble",
        "eye",
        "virtue",
        "friendship",
        "happiness",
        "death",
        "adventure",
        "véra",
        "rapture",
        "heart",
        "girl",
        "thing",
        "wife",
        "despot",
        "kurágin",
        "childhood",
        "tear",
        "power",
        "affair",
        "cloud",
        "word",
        "mankind"
    ],
    "explain": [
        "movement",
        "fact",
        "count",
        "18th",
        "advantage",
        "nichola",
        "plan",
        "treatment",
        "freemasonry",
        "paulucci",
        "detail",
        "yesterday",
        "voice",
        "matter",
        "resultant",
        "relation",
        "condition",
        "connection"
    ],
    "include": [
        "anna",
        "anatole",
        "chief",
        "prince",
        "space"
    ],
    "follow": [
        "anna",
        "day",
        "cart",
        "line",
        "letter",
        "princess",
        "passage",
        "other",
        "soldier",
        "budget",
        "example",
        "opera",
        "direction",
        "balashëv",
        "pfuel",
        "infantry",
        "movement",
        "prophecy",
        "significance",
        "order",
        "track",
        "carriage",
        "abandonment",
        "murat",
        "communication",
        "army",
        "word",
        "battle",
        "announcement",
        "step",
        "peasant",
        "enemy",
        "morning",
        "detail",
        "consideration",
        "path"
    ],
    "see": [
        "count",
        "emperor",
        "princess",
        "thing",
        "brother",
        "enemy",
        "mademoiselle",
        "anatole",
        "people",
        "light",
        "carriage",
        "battle",
        "soldier",
        "hussar",
        "portrait",
        "effect",
        "immense",
        "cossack",
        "prisoner",
        "rostóvs",
        "reign",
        "group",
        "horse",
        "hound",
        "possibility",
        "anna",
        "child",
        "hundred",
        "pistol",
        "expression",
        "handsomer",
        "doll",
        "your",
        "manifesto",
        "state",
        "trunk",
        "regiment",
        "seriousness",
        "skirmisher",
        "nesvítski",
        "disposition",
        "rain",
        "gunner",
        "front",
        "pitch",
        "pávlograd",
        "day",
        "gaze",
        "impression",
        "tear",
        "distraught",
        "puff",
        "uneasiness",
        "troop",
        "turret",
        "today",
        "man",
        "duport",
        "salver",
        "success",
        "véra",
        "steward",
        "picket",
        "quartermaster",
        "raft",
        "table",
        "preobrazhénsk",
        "marshal",
        "anteroom",
        "uniform",
        "plume",
        "england",
        "countess",
        "whip",
        "queer",
        "moonlight",
        "coffin",
        "evil",
        "coldness",
        "balashëv",
        "dragoon",
        "dessalle",
        "governor",
        "girl",
        "hand",
        "color",
        "peasant",
        "battlefield",
        "position",
        "calf",
        "chivalry",
        "king",
        "field",
        "attack",
        "action",
        "russian",
        "crowd",
        "movement",
        "valve",
        "blood",
        "intervention",
        "knot",
        "traveler",
        "city",
        "colonel",
        "village",
        "aunt",
        "nichola",
        "church",
        "lot",
        "kurágin",
        "bennigsen",
        "infantry",
        "baggage",
        "cupola",
        "frenchman",
        "thousand",
        "eye",
        "cudgel",
        "vision",
        "body",
        "deadness",
        "doctor",
        "savélich",
        "allusion",
        "force",
        "beauty",
        "woman",
        "charm",
        "treason",
        "chief",
        "devil",
        "law",
        "event"
    ],
    "talk": [
        "nonsense",
        "rubbish",
        "business",
        "sense",
        "lot",
        "politic",
        "tea",
        "secret",
        "card",
        "papa",
        "dressmaker",
        "thing",
        "officer",
        "patriotism"
    ],
    "help": [
        "man",
        "england",
        "lad",
        "bit",
        "sort",
        "hand",
        "peasant",
        "matter",
        "countess",
        "officer",
        "bear",
        "nichola",
        "princess"
    ],
    "open": [
        "door",
        "window",
        "space",
        "eye",
        "fire",
        "doorway",
        "portmanteau",
        "shop",
        "cab",
        "expression",
        "word",
        "exercise",
        "veil",
        "restaurant",
        "shirt",
        "whiff",
        "bedroom",
        "flower",
        "carriage",
        "shutter",
        "ball",
        "field",
        "letter",
        "desk",
        "ballroom",
        "bearskin",
        "gentleman",
        "struggle",
        "sky",
        "barrel",
        "coach",
        "kitchen",
        "declivity",
        "padlock",
        "hand",
        "country",
        "wound",
        "world",
        "heart",
        "mouth"
    ],
    "drink": [
        "tea",
        "shop",
        "bottle",
        "lorrain",
        "today",
        "vodka",
        "silver",
        "coffee",
        "chicken",
        "day",
        "store"
    ],
    "push": [
        "anatole",
        "letter",
        "nesvítski",
        "gun",
        "cart"
    ],
    "inspire": [
        "respect",
        "expression",
        "confidence",
        "people"
    ],
    "enjoy": [
        "life",
        "feeling",
        "yesterday",
        "evening",
        "beauty",
        "respect"
    ],
    "announce": [
        "countess",
        "peace",
        "approach",
        "husband",
        "perturbation",
        "victory",
        "trophy",
        "roll"
    ],
    "sit": [
        "room",
        "motionless",
        "count",
        "anatole",
        "countess",
        "other",
        "member",
        "ruddy",
        "anna",
        "indoor",
        "chanter",
        "barclay",
        "uvárov",
        "peasant",
        "woman",
        "dog",
        "princess"
    ],
    "laugh": [
        "voice",
        "eye",
        "regimental",
        "und",
        "countenance",
        "expression",
        "afresh",
        "glance",
        "other",
        "nichola",
        "child"
    ],
    "celebrate": [
        "petersburg",
        "victory",
        "miniaturist",
        "beauty",
        "award"
    ],
    "search": [
        "glance"
    ],
    "turn": [
        "count",
        "purple",
        "conversation",
        "spindle",
        "snuffbox",
        "bottom",
        "outward",
        "gun",
        "métivier",
        "head",
        "collar",
        "corner",
        "shoulder",
        "enemy"
    ],
    "run": [
        "animal",
        "sword",
        "risk",
        "gentleman",
        "hither",
        "soldier",
        "foot"
    ],
    "read": [
        "letter",
        "paper",
        "scripture",
        "dispatch",
        "epistle",
        "congratulation",
        "confirmation",
        "address",
        "statute",
        "exhortation",
        "book",
        "princess",
        "love",
        "inscription",
        "appeal",
        "life",
        "psalm",
        "sheet",
        "sirin",
        "novel",
        "sympathy",
        "gospel"
    ],
    "find": [
        "expression",
        "way",
        "happiness",
        "pleasure",
        "place",
        "justification",
        "word",
        "family",
        "sum",
        "suvórovs",
        "page",
        "husband",
        "vent",
        "colonel",
        "vehicle",
        "blood",
        "courage",
        "count",
        "cream",
        "letter",
        "baby",
        "boy",
        "plant",
        "country",
        "time",
        "form",
        "amusement",
        "tutor",
        "state",
        "quarry",
        "chord",
        "occupation",
        "sleeve",
        "phrase",
        "davout",
        "life",
        "kurágin",
        "barclay",
        "corner",
        "cossack",
        "sign",
        "symptom",
        "relief",
        "reason",
        "law",
        "possibility",
        "chief",
        "milorádovich",
        "protection",
        "food",
        "instance",
        "government",
        "component"
    ],
    "clean": [
        "shirt",
        "one",
        "pocket",
        "quarter",
        "troop",
        "pair",
        "handkerchief",
        "life",
        "heart",
        "folk",
        "bed"
    ],
    "arrive": [
        "countess",
        "princess",
        "officer",
        "bell",
        "man",
        "frenchman"
    ],
    "sing": [
        "song",
        "master",
        "tune",
        "today",
        "air",
        "prayer",
        "girl",
        "soldier",
        "service"
    ],
    "play": [
        "part",
        "card",
        "fool",
        "chess",
        "patience",
        "figure",
        "hero",
        "prelude",
        "polonaise",
        "piece",
        "rubber",
        "ring",
        "game",
        "king",
        "draught",
        "role"
    ],
    "prepare": [
        "onlooker",
        "countess",
        "card",
        "tea",
        "seeker",
        "man",
        "firework",
        "asylum",
        "surprise",
        "opinion",
        "bed",
        "sire",
        "officer",
        "winter",
        "provision",
        "expedition"
    ],
    "dance": [
        "shoe",
        "room",
        "master",
        "song",
        "count",
        "soldier",
        "lesson",
        "emperor",
        "Trepák",
        "Pelagéya",
        "trepák"
    ],
    "change": [
        "expression",
        "place",
        "horse",
        "clothe",
        "battle",
        "character",
        "shadow",
        "role",
        "water",
        "movement",
        "man",
        "candle",
        "hand"
    ],
    "write": [
        "table",
        "letter",
        "history",
        "code",
        "bilíbin",
        "king",
        "law",
        "speech",
        "matter",
        "countess",
        "order",
        "word",
        "confirmation",
        "emperor",
        "governor",
        "command",
        "disposition",
        "proclamation"
    ],
    "close": [
        "door",
        "eye",
        "carriage",
        "quarter",
        "exercise",
        "handwriting",
        "latch",
        "curtain",
        "touch",
        "proximity",
        "thing",
        "shop",
        "shutter",
        "window",
        "knife"
    ],
    "return": [
        "home",
        "journey",
        "count",
        "glove",
        "bilíbin",
        "battalion",
        "doctor",
        "nichola",
        "anatole",
        "balashëv",
        "hussar",
        "tear",
        "voice",
        "thence",
        "davout"
    ],
    "stand": [
        "motionless",
        "carriage",
        "priest",
        "aide",
        "miniature",
        "sight",
        "lad",
        "man",
        "oak",
        "year",
        "minute",
        "guard",
        "peasant",
        "glass",
        "notability",
        "infantry",
        "flèche",
        "crowd",
        "army",
        "cart",
        "gerásim",
        "row",
        "mother"
    ],
    "facilitate": [
        "activity"
    ],
    "forget": [
        "law",
        "battery",
        "danger",
        "sovereign",
        "morning",
        "thousand",
        "part",
        "official"
    ],
    "confirm": [
        "order",
        "truth",
        "news",
        "opinion",
        "fact",
        "supposition"
    ],
    "speak": [
        "word",
        "princess",
        "truth",
        "curtain",
        "balashëv",
        "gentleman",
        "today"
    ],
    "call": [
        "princess",
        "friend",
        "genius",
        "Jackdaw",
        "power",
        "law",
        "halt",
        "Cossack",
        "colonel",
        "milorádovich",
        "enchantress",
        "conscience",
        "nurse",
        "ulyulyu",
        "room",
        "Balagá",
        "king",
        "officer",
        "war",
        "heroism",
        "coachman",
        "berthier",
        "standard",
        "coward",
        "food",
        "count",
        "landowner",
        "karabákh",
        "hero",
        "battle",
        "roll",
        "science",
        "culture",
        "idea"
    ],
    "wait": [
        "bit",
        "room",
        "moment",
        "minute",
        "opportunity",
        "nichola",
        "announce",
        "year"
    ],
    "admit": [
        "possibility",
        "conception",
        "idea",
        "public",
        "doctor",
        "person",
        "mademoiselle",
        "existence",
        "greatness",
        "thousand",
        "law"
    ],
    "share": [
        "room",
        "defeat",
        "adoration",
        "dinner"
    ],
    "train": [
        "artillery",
        "driver",
        "trotter",
        "family",
        "military",
        "band",
        "singer"
    ],
    "examine": [
        "position",
        "action",
        "event",
        "act",
        "countryside",
        "battlefield",
        "princess",
        "plan",
        "brood",
        "seam",
        "relation",
        "case",
        "man",
        "inevitability",
        "freedom",
        "manifestation"
    ],
    "eat": [
        "apple",
        "bread",
        "porridge",
        "mash",
        "potato",
        "bit",
        "drank",
        "sleep"
    ],
    "stop": [
        "infantry",
        "regiment",
        "company",
        "rotary",
        "horse",
        "animal",
        "minute",
        "sigh",
        "robbery",
        "pillage"
    ],
    "extend": [
        "position",
        "hand",
        "line",
        "future",
        "frontier"
    ],
    "describe": [
        "event",
        "condition",
        "activity",
        "engagement",
        "princess",
        "thank",
        "military",
        "depth",
        "action",
        "position",
        "woman",
        "horror",
        "war",
        "campaign",
        "movement"
    ],
    "decide": [
        "matter",
        "refusal",
        "family"
    ],
    "recognize": [
        "motion",
        "world",
        "sire",
        "bonaparte",
        "mummer",
        "cry",
        "voice",
        "wolzogen",
        "anatole",
        "position",
        "place",
        "princess",
        "district",
        "appearance",
        "value",
        "insignificance",
        "divinity",
        "defect",
        "subjection",
        "dependence"
    ],
    "fall": [
        "snow",
        "horse",
        "woman",
        "bomb",
        "body",
        "wall"
    ],
    "build": [
        "shelter",
        "chantry",
        "hospital",
        "operation"
    ],
    "teach": [
        "other",
        "man",
        "hen"
    ],
    "remember": [
        "word",
        "story",
        "nichola",
        "day",
        "expression",
        "countess",
        "peasant",
        "light",
        "family",
        "Sventsyáni",
        "anatole",
        "sire",
        "meadow",
        "connection",
        "moment",
        "torture"
    ],
    "work": [
        "screw",
        "assistance",
        "dry",
        "education",
        "day",
        "afresh"
    ],
    "jump": [
        "Túshin",
        "ditch"
    ],
    "sign": [
        "paper",
        "deed",
        "receipt",
        "alexander",
        "glory",
        "disposition"
    ],
    "advise": [
        "architect",
        "nichola"
    ],
    "propose": [
        "marriage",
        "battle",
        "toast",
        "treaty",
        "tomorrow",
        "peace"
    ],
    "listen": [
        "langeron",
        "nichola",
        "Balagá",
        "count",
        "drónushka",
        "tranquillity"
    ],
    "gather": [
        "lad",
        "courage",
        "group",
        "clothe",
        "mist",
        "thing",
        "honey",
        "pollen"
    ],
    "encourage": [
        "word",
        "culture"
    ],
    "walk": [
        "pace",
        "mile",
        "treadmill",
        "devil",
        "officer",
        "peasant",
        "dite"
    ],
    "protect": [
        "woman",
        "battery",
        "cart"
    ],
    "select": [
        "moment",
        "company",
        "place",
        "element",
        "calèche",
        "indication"
    ],
    "borrow": [
        "money"
    ],
    "cook": [
        "call",
        "Zinaída",
        "coachman",
        "wood"
    ],
    "support": [
        "coverlet",
        "battery"
    ],
    "improve": [
        "mankind",
        "position",
        "life"
    ],
    "plan": [
        "plan",
        "arrangement",
        "refutation",
        "pencil",
        "nichola",
        "thought"
    ],
    "sleep": [
        "bit",
        "princess",
        "place",
        "man",
        "nichola"
    ],
    "introduce": [
        "examination",
        "partner",
        "hospital",
        "conception",
        "power"
    ],
    "create": [
        "excitement",
        "impression",
        "situation"
    ],
    "translate": [
        "article",
        "thing"
    ],
    "hope": [
        "princess",
        "count",
        "light",
        "inspire",
        "emperor"
    ],
    "warn": [
        "finger"
    ],
    "invite": [
        "nichola",
        "customer"
    ],
    "manage": [
        "matter",
        "daughter",
        "debate",
        "people",
        "business",
        "affair"
    ],
    "review": [
        "troop",
        "principal"
    ],
    "conclude": [
        "peace"
    ],
    "promote": [
        "captain"
    ],
    "allow": [
        "cavalry",
        "time",
        "madame",
        "troop",
        "orphan",
        "family"
    ],
    "report": [
        "abandonment",
        "sir",
        "country",
        "incident",
        "matter",
        "project"
    ],
    "criticize": [
        "position"
    ],
    "discover": [
        "law"
    ],
    "investigate": [
        "matter"
    ],
    "calculate": [
        "expression"
    ],
    "yell": [
        "officer"
    ],
    "belong": [
        "credit"
    ],
    "apply": [
        "troop",
        "submission",
        "word"
    ],
    "estimate": [
        "architect"
    ],
    "contribute": [
        "church"
    ],
    "organize": [
        "distribution"
    ],
    "guess": [
        "reason"
    ],
    "analyze": [
        "property"
    ],
    "develop": [
        "body"
    ],
    "try": [
        "threat"
    ],
    "connect": [
        "effect"
    ]
}